{
 "id": "10",
 "error": 0.228654832724272,
 "resolution": {
  "height": 480,
  "width": 640
 },
 "intrinsic": {
  "shape": {
   "dims": [
    {
     "size": 3,
     "name": "rows"
    },
    {
     "size": 3,
     "name": "cols"
    }
   ]
  },
  "type": "DOUBLE_TYPE",
  "floats": [],
  "doubles": [
   605.344210556911,
   0,
   331.98123318490138,
   0,
   603.9338608637338,
   227.90010759315169,
   0,
   0,
   1
  ],
  "ints32": [],
  "ints64": []
 },
 "distortion": {
  "shape": {
   "dims": [
    {
     "size": 1,
     "name": "rows"
    },
    {
     "size": 5,
     "name": "cols"
    }
   ]
  },
  "type": "DOUBLE_TYPE",
  "floats": [],
  "doubles": [
   0.091670923791937489,
   -0.021236979611192447,
   -0.006436891142066645,
   0.0061064789804514477,
   -1.492688601869292
  ],
  "ints32": [],
  "ints64": []
 },
 "extrinsic": [],
 "calibratedAt": "2018-07-09T15:59:31.037026895Z"
}
