{
 "id": "3",
 "error": 0.35163487845368657,
 "resolution": {
  "height": 728,
  "width": 1288
 },
 "intrinsic": {
  "shape": {
   "dims": [
    {
     "size": 3,
     "name": "rows"
    },
    {
     "size": 3,
     "name": "cols"
    }
   ]
  },
  "type": "DOUBLE_TYPE",
  "floats": [],
  "doubles": [
   1019.2147972803808,
   0,
   654.1441616363262,
   0,
   1019.5252939898667,
   394.5672641096034,
   0,
   0,
   1
  ],
  "ints32": [],
  "ints64": []
 },
 "distortion": {
  "shape": {
   "dims": [
    {
     "size": 1,
     "name": "rows"
    },
    {
     "size": 5,
     "name": "cols"
    }
   ]
  },
  "type": "DOUBLE_TYPE",
  "floats": [],
  "doubles": [
   -0.213138418454295,
   0.16954581195524907,
   0.0038080468530335429,
   0.0049068991447649563,
   0.078403474141225935
  ],
  "ints32": [],
  "ints64": []
 },
 "extrinsic": [
  {
   "from": "1000",
   "to": "3",
   "tf": {
    "shape": {
     "dims": [
      {
       "size": 4,
       "name": "rows"
      },
      {
       "size": 4,
       "name": "cols"
      }
     ]
    },
    "type": "DOUBLE_TYPE",
    "floats": [],
    "doubles": [
     -0.54129210556339669,
     -0.840296433660043,
     0.030079229261358253,
     -1.038808031493047,
     -0.50952253272849635,
     0.29934114614334706,
     -0.80671039838812364,
     0.046984716585451669,
     0.66887191979980942,
     -0.45199201519916232,
     -0.59018096639888107,
     5.0266433560273152,
     0,
     0,
     0,
     1
    ],
    "ints32": [],
    "ints64": []
   }
  }
 ],
 "calibratedAt": "2018-09-18T22:12:11.493515961Z"
}
